young/__init__.py
young/__root__.py
young/__version__.py
young/common/__init__.py
young/common/constants.py
young/common/dataset.py
young/common/globals.py
young/common/vocabulary.py
young/nmt/__init__.py
young/nmt/young_nmt.py
young/nmt/models/__init__.py
young/nmt/models/base.py
young/nmt/models/rnnsearch.py
young/nmt/modules/__init__.py
young/nmt/modules/attentions.py
young/nmt/modules/decoders.py
young/nmt/modules/embedding.py
young/nmt/modules/encoders.py
young/nmt/modules/generators.py
young/nmt/modules/rnn.py
young/nmt/utilities/__init__.py
young/nmt/utilities/argument.py
young/nmt/utilities/criterion.py
young/nmt/utilities/initializer.py
young/nmt/utilities/optimizer.py
young/nmt/utilities/scheduler.py
young/nmt/utilities/searcher.py
young/nmt/utilities/tensor_handler.py
young/smt/__init__.py
young_cli/__init__.py
young-0.0.1.2019a0.dist-info/LICENSE
young-0.0.1.2019a0.dist-info/METADATA
young-0.0.1.2019a0.dist-info/WHEEL
young-0.0.1.2019a0.dist-info/top_level.txt
young-0.0.1.2019a0.dist-info/RECORD
